{
    "solutions": [
  { "word": "earth", "id": 1 },
  { "word": "stone", "id": 2 },
  { "word": "plant", "id": 3 },
  { "word": "river", "id": 4 },
  { "word": "cloud", "id": 5 },
  { "word": "ocean", "id": 6 },
  { "word": "flame", "id": 7 },
  { "word": "storm", "id": 8 },
  { "word": "grass", "id": 9 },
  { "word": "mines", "id": 10 },
  { "word": "blaze", "id": 11 },
  { "word": "quake", "id": 12 },
  { "word": "drift", "id": 13 },
  { "word": "globe", "id": 14 },
  { "word": "bloom", "id": 15 },
  { "word": "shell", "id": 16 },
  { "word": "trail", "id": 17 },
  { "word": "valve", "id": 18 },
  { "word": "crust", "id": 19 },
  { "word": "slope", "id": 20 },
  { "word": "grain", "id": 21 },
  { "word": "shore", "id": 22 },
  { "word": "basin", "id": 23 },
  { "word": "creek", "id": 24 },
  { "word": "grove", "id": 25 },
  { "word": "beach", "id": 26 },
  { "word": "dunes", "id": 27 },
  { "word": "frost", "id": 28 },
  { "word": "rocks", "id": 29 },
  { "word": "hills", "id": 30 },
  { "word": "wheat", "id": 31 },
  { "word": "roots", "id": 32 },
  { "word": "lemon", "id": 33 },
  { "word": "fruit", "id": 34 },
  { "word": "amber", "id": 35 },
  { "word": "chili", "id": 36 },
  { "word": "flock", "id": 37 },
  { "word": "winds", "id": 38 },
  { "word": "storm", "id": 39 },
  { "word": "night", "id": 40 },
  { "word": "cabin", "id": 41 },
  { "word": "meadow", "id": 42 },
  { "word": "cliff", "id": 43 },
  { "word": "caves", "id": 44 },
  { "word": "bison", "id": 45 },
  { "word": "cedar", "id": 46 },
  { "word": "ashen", "id": 47 },
  { "word": "rains", "id": 48 },
  { "word": "lilac", "id": 49 },
  { "word": "gleam", "id": 50 },
  { "word": "flood", "id": 51 },
  { "word": "swamp", "id": 52 },
  { "word": "gorge", "id": 53 },
  { "word": "flora", "id": 54 },
  { "word": "thick", "id": 55 },
  { "word": "crown", "id": 56 },
  { "word": "reeds", "id": 57 },
  { "word": "brook", "id": 58 },
  { "word": "raven", "id": 59 },
  { "word": "tulip", "id": 60 },
  { "word": "pines", "id": 61 },
  { "word": "sands", "id": 62 },
  { "word": "foggy", "id": 63 },
  { "word": "whirl", "id": 64 },
  { "word": "pearl", "id": 65 },
  { "word": "wooly", "id": 66 },
  { "word": "rocks", "id": 67 },
  { "word": "mossy", "id": 68 },
  { "word": "shrub", "id": 69 },
  { "word": "ledge", "id": 70 }
    ],

    "letters": [
      { "id": 1, "key": "Q" },
      { "id": 2, "key": "W" },
      { "id": 3, "key": "E" },
      { "id": 4, "key": "R" },
      { "id": 5, "key": "T" },
      { "id": 6, "key": "Y" },
      { "id": 7, "key": "U" },
      { "id": 8, "key": "I" },
      { "id": 9, "key": "O" },
      { "id": 10, "key": "P" },
      { "id": 11, "key": "A" },
      { "id": 12, "key": "S" },
      { "id": 13, "key": "D" },
      { "id": 14, "key": "F" },
      { "id": 15, "key": "G" },
      { "id": 16, "key": "H" },
      { "id": 17, "key": "J" },
      { "id": 18, "key": "K" },
      { "id": 19, "key": "L" },
      { "id": 27, "key": "ENTER" },
      { "id": 20, "key": "Z" },
      { "id": 21, "key": "X" },
      { "id": 22, "key": "C" },
      { "id": 23, "key": "V" },
      { "id": 24, "key": "B" },
      { "id": 25, "key": "N" },
      { "id": 26, "key": "M" },
      { "id": 28, "key": "BACK" }
    ]
    
}